componentsDjangoType/__init__.py
componentsDjangoType/management/__init__.py
componentsDjangoType/management/commands/__init__.py
componentsDjangoType/management/commands/createcomponent.py
componentsDjangoType-0.0.3.dist-info/LICENSE
componentsDjangoType-0.0.3.dist-info/METADATA
componentsDjangoType-0.0.3.dist-info/WHEEL
componentsDjangoType-0.0.3.dist-info/top_level.txt
componentsDjangoType-0.0.3.dist-info/RECORD
