Metadata-Version: 2.1
Name: componentsDjangoType
Version: 0.0.3
Summary: A Django app for creating HTML components
Home-page: https://github.com/jose-CR/componentsDjangoType
Author: Alejandro
Author-email: hjosealejandro21@gmail.com
License: MIT
Platform: UNKNOWN
Classifier: Environment :: Web Environment
Classifier: Framework :: Django
Classifier: Intended Audience :: Developers
Classifier: License :: OSI Approved :: MIT License
Classifier: Operating System :: OS Independent
Classifier: Programming Language :: Python
Classifier: Programming Language :: Python :: 3
Classifier: Programming Language :: Python :: 3.7
Classifier: Framework :: Django :: 3.2
License-File: LICENSE
Requires-Dist: Django (>=3.2)
